ndpatch/__init__.py
ndpatch/ndpatch.py
ndpatch/tests/__init__.py
ndpatch/tests/test_ndpatch.py
ndpatch-0.0.2.dist-info/LICENSE.txt
ndpatch-0.0.2.dist-info/METADATA
ndpatch-0.0.2.dist-info/WHEEL
ndpatch-0.0.2.dist-info/top_level.txt
ndpatch-0.0.2.dist-info/RECORD
