Metadata-Version: 2.1
Name: ndpatch
Version: 0.0.2
Summary: Extract arbitrary n-dimensional regions from ndarrays.
Home-page: https://github.com/ashkarin/ndpatch
Author: Andrei Shkarin
Author-email: andrei.shkarin@gmail.com
License: UNKNOWN
Project-URL: Source, https://github.com/ashkarin/ndpatch
Project-URL: Bug Reports, https://github.com/ashkarin/ndpatch/issues
Keywords: ndarray patch region data development
Platform: UNKNOWN
Classifier: Development Status :: 3 - Alpha
Classifier: Intended Audience :: Developers
Classifier: Intended Audience :: Science/Research
Classifier: License :: OSI Approved :: MIT License
Classifier: Topic :: Software Development :: Libraries :: Python Modules
Requires-Dist: numpy
